Lab2/Lab2/code/MUX_2to1.v
//Subject:     CO project 2 - MUX 221
//--------------------------------------------------------------------------------
//Version:     1
//--------------------------------------------------------------------------------
//Writer:      0616223 0616059
//----------------------------------------------
//Date:        4/27
//----------------------------------------------
//Description: multiplexer 2 to 1
//--------------------------------------------------------------------------------
     
module MUX_2to1(
               data0_i,
               data1_i,
               select_i,
               data_o
               );

parameter size = 0;			   
			
//I/O ports               
input   [size-1:0] data0_i;          
input   [size-1:0] data1_i;
input              select_i;
output  [size-1:0] data_o; 

//Internal Signals
reg     [size-1:0] data_o;

//Main function

always @(*)
	begin

		case(select_i)
			1'b0 : data_o = data0_i;
			1'b1 : data_o = data1_i;
		endcase

	end

endmodule

Lab2/Lab2/code/Shift_Left_Two_32.v
//Subject:      CO project 2 - Shift_Left_Two_32
//--------------------------------------------------------------------------------
//Version:     1
//--------------------------------------------------------------------------------
//Description: shift data left two bits
//--------------------------------------------------------------------------------

module Shift_Left_Two_32(
    data_i,
    data_o
    );

//I/O ports                    
input [32-1:0] data_i;

output [32-1:0] data_o;

reg [31:0] i,data_o;

//shift left 2

always @( * )
	begin
	
	data_o[0] = 1'b0;
	data_o[1] = 1'b0;

	for(i=2; i<=31; i=i+1)
		begin
		data_o[i] = data_i[i-2];
		end
		
	end

endmodule

Lab2/Lab2/code/Adder.v
//Subject:     CO project 2 - Adder
//--------------------------------------------------------------------------------
//Version:     1
//--------------------------------------------------------------------------------
//Writer:      0616223 0616059
//----------------------------------------------
//Date:        4/27 
//----------------------------------------------
//Description: add two 32 bits data
//--------------------------------------------------------------------------------

module Adder(
  src1_i,
	src2_i,
	sum_o
	);
     
//I/O ports
input  [32-1:0]  src1_i;
input  [32-1:0]	 src2_i;
output [32-1:0]	 sum_o;

//Internal Signals
wire    [32-1:0]	 sum_o;

//Parameter
    
//Main function

assign sum_o = src1_i + src2_i;

endmodule

Lab2/Lab2/code/ALU.v
//Subject:     CO project 2 - ALU
//--------------------------------------------------------------------------------
//Version:     1
//--------------------------------------------------------------------------------
//Writer:      0616223 0616059
//----------------------------------------------
//Date:        4/27
//----------------------------------------------
//Description: ALU with ALUCtrl input
//--------------------------------------------------------------------------------

module ALU(
    src1_i,
	src2_i,
	ctrl_i,
	result_o,
	zero_o
	);
     
//I/O ports
input  [32-1:0]  src1_i;
input  [32-1:0]	 src2_i;
input  [4-1:0]   ctrl_i;

output [32-1:0]	 result_o;
output           zero_o;

//Internal signals
reg    [32-1:0]  result_o;
wire             zero_o;

//Parameter
integer i;
reg [15:0] temp;
reg [4:0]  temp_2;
reg [31:0] temp_3;
//Main function

always@ ( * )
	begin
		case(ctrl_i)
			4'b0010:
				begin
					result_o = src1_i + src2_i;
				end
			4'b0110:
				begin
					result_o = src1_i + ~src2_i + 1;
				end
			4'b0000:
				begin
					result_o = src1_i & src2_i;
				end
			4'b0001:
				begin
					result_o = src1_i | src2_i;
				end
			4'b0111:
				begin
					result_o = src1_i + ~src2_i + 1;
					if(result_o[31])begin
						result_o = 1;
					end
					else begin
						result_o = 0;
					end
				end
			4'b1101 : //sra
				begin
					temp_2 = src1_i[10:6];
					result_o = src2_i >> temp_2;
					if(src2_i[31])begin
						for(temp_2=temp_2;temp_2>0;temp_2=temp_2-1)
							begin
								result_o[31-temp_2+1]=1'b1;
							end
					end
				end
			4'b1001 : //srav
				begin
					result_o = src2_i >> src1_i;
					if(src2_i[31])begin
					temp_3=src1_i;
						for(temp_3=temp_3;temp_3>0;temp_3=temp_3-1)
							begin
								result_o[31-temp_3+1]=1'b1;
							end
					end
				end
			4'b1000 : //lui
				begin
					temp = src2_i[15:0];
					result_o = temp << 16; 
				end
			4'b1110 :
				begin
					if(src1_i >= 32'd65536)begin
						result_o = 0;
					end
					else begin
						if(src1_i >= src2_i)begin
							result_o = 0;
						end
						else begin
							result_o = 1;
						end
					end
				end
			4'b1111 :
				begin
					result_o = src1_i + ~src2_i + 1;
					if(result_o == 0)begin
						result_o = 1;
					end
					else begin
						result_o = 0;
					end
				end
		endcase
	end

assign zero_o = result_o == 0 ? 1 : 0;
endmodule

Lab2/Lab2/code/Sign_Extend.v
//Subject:     CO project 2 - Sign extend
//--------------------------------------------------------------------------------
//Version:     1
//--------------------------------------------------------------------------------
//Writer:      0616223 0616059
//----------------------------------------------
//Date:        4/27	
//----------------------------------------------
//Description: extend 16 bits to 32 bits
//--------------------------------------------------------------------------------

module Sign_Extend(
    data_i,
    data_o
    );
               
//I/O ports
input   [16-1:0] data_i;
output  [32-1:0] data_o;

//Internal Signals
reg     [32-1:0] data_o;
reg     [31:0] i;
//Sign extended

always @(data_i)
	begin
		
		for( i=0 ; i<=15 ; i=i+1)
			data_o[i]=data_i[i];
		
		for( i=16 ; i<=31 ; i=i+1)
			data_o[i]=data_i[15];
	end

endmodule

Lab2/Lab2/code/ALU_Ctrl.v
//Subject:     CO project 2 - ALU Controller
//--------------------------------------------------------------------------------
//Version:     1
//--------------------------------------------------------------------------------
//Writer:      0616223 0616059
//----------------------------------------------
//Date:        4/27
//----------------------------------------------
//Description: determine which control code should give to ALU
//--------------------------------------------------------------------------------

module ALU_Ctrl(
          funct_i,
          ALUOp_i,
          ALUCtrl_o
          );
          
//I/O ports 
input      [6-1:0] funct_i;
input      [3-1:0] ALUOp_i;

output     [4-1:0] ALUCtrl_o;    
     
//Internal Signals
reg        [4-1:0] ALUCtrl_o;

//Parameter

       
//Select exact operation
always @( * )
	begin
		case(ALUOp_i)

			3'b010 : //R-type
				begin
					case(funct_i)
						6'b100001 : ALUCtrl_o = 4'b0010; //add
						
						6'b100011 : ALUCtrl_o = 4'b0110; //sub
						
						6'b100100 : ALUCtrl_o = 4'b0000; //and
						
						6'b100101 : ALUCtrl_o = 4'b0001; //or

						6'b101010 : ALUCtrl_o = 4'b0111; //slt

						6'b000011 : ALUCtrl_o = 4'b1101; //sra

						6'b000111 : ALUCtrl_o = 4'b1001; //srav
					endcase
				end
			
			3'b001 : ALUCtrl_o = 4'b0110;// beq
			
			3'b011 : ALUCtrl_o = 4'b1111;// bne
			
			3'b100 : ALUCtrl_o = 4'b0010;// addi
			
			3'b101 : ALUCtrl_o = 4'b1110;// sltiu
			
			3'b110 : ALUCtrl_o = 4'b1000;// lui
			
			3'b111 : ALUCtrl_o = 4'b0001;// ori
		endcase
	end
endmodule

Lab2/Lab2/code/Decoder.v
//Subject:     CO project 2 - Decoder
//--------------------------------------------------------------------------------
//Version:     1
//--------------------------------------------------------------------------------
//Writer:      0616223 0616059
//----------------------------------------------
//Date:        4/27
//----------------------------------------------
//Description: instruction decoder
//--------------------------------------------------------------------------------

module Decoder(
  instr_op_i,
	RegWrite_o,
	ALU_op_o,
	ALUSrc_o,
	RegDst_o,
	Branch_o
	);
     
//I/O ports
input  [6-1:0] instr_op_i;

output         RegWrite_o;
output [3-1:0] ALU_op_o;
output         ALUSrc_o;
output         RegDst_o;
output         Branch_o;
 
//Internal Signals
reg    [3-1:0] ALU_op_o;
reg            ALUSrc_o;
reg            RegWrite_o;
reg            RegDst_o;
reg            Branch_o;

//Parameter


//Main function

always @( * )
	
	begin

	case(instr_op_i)

		6'b000000 : 
			begin 
				ALU_op_o = 3'b010; 
				ALUSrc_o = 1'b0; 
				RegWrite_o = 1'b1;
				RegDst_o = 1'b1;
				Branch_o = 1'b0;
			end

		6'b001000 : // aadi
			begin
				ALU_op_o = 3'b100;
				ALUSrc_o = 1'b1;
				RegWrite_o = 1'b1;
				RegDst_o = 1'b0;
				Branch_o = 1'b0;
			end

		6'b001011 : // sltiu 
			begin
				ALU_op_o = 3'b101;
				ALUSrc_o = 1'b1;
				RegWrite_o = 1'b1;
				RegDst_o = 1'b0;
				Branch_o = 1'b0;
			end	

		6'b000100 : // beq
			begin
				ALU_op_o = 3'b001;
				ALUSrc_o = 1'b0;
				RegWrite_o = 1'b0;
				Branch_o = 1'b1;
			end

		6'b001111 : //lui
			begin
				ALU_op_o = 3'b110;
				ALUSrc_o = 1'b1;
				RegWrite_o = 1'b1;
				RegDst_o = 1'b0;
				Branch_o = 1'b0;
			end

		6'b001101 : //ori
			begin
				ALU_op_o = 3'b111;
				ALUSrc_o = 1'b1;
				RegWrite_o = 1'b1;
				RegDst_o = 1'b0;
				Branch_o = 1'b0;
			end

		6'b000101 : //bne
			begin
				ALU_op_o = 3'b011;
				ALUSrc_o = 1'b0;
				RegWrite_o = 1'b0;
				Branch_o = 1'b1;
			end



	endcase

	end

endmodule

Lab2/Lab2/code/Reg_File.v
//Subject:     CO project 2 - Register File
//--------------------------------------------------------------------------------
//Version:     1
//--------------------------------------------------------------------------------
//Writer:      0616223 0616059
//----------------------------------------------
//Date:        4/27
//----------------------------------------------
//Description: main register
//--------------------------------------------------------------------------------
module Reg_File(
    clk_i,
	rst_i,
    RSaddr_i,
    RTaddr_i,
    RDaddr_i,
    RDdata_i,
    RegWrite_i,
    RSdata_o,
    RTdata_o
    );
          
//I/O ports
input           clk_i;
input           rst_i;
input           RegWrite_i;
input  [5-1:0]  RSaddr_i;
input  [5-1:0]  RTaddr_i;
input  [5-1:0]  RDaddr_i;
input  [32-1:0] RDdata_i;

output [32-1:0] RSdata_o;
output [32-1:0] RTdata_o;   

//Internal signals/registers           
reg  signed [32-1:0] Reg_File [0:32-1];     //32 word registers
wire        [32-1:0] RSdata_o;
wire        [32-1:0] RTdata_o;

//Read the data
assign RSdata_o = Reg_File[RSaddr_i] ;
assign RTdata_o = Reg_File[RTaddr_i] ;   

//Writing data when postive edge clk_i and RegWrite_i was set.
always @( posedge rst_i or posedge clk_i  ) begin
    if(rst_i == 0) begin
	    Reg_File[0]  <= 0; Reg_File[1]  <= 0; Reg_File[2]  <= 0; Reg_File[3]  <= 0;
	    Reg_File[4]  <= 0; Reg_File[5]  <= 0; Reg_File[6]  <= 0; Reg_File[7]  <= 0;
        Reg_File[8]  <= 0; Reg_File[9]  <= 0; Reg_File[10] <= 0; Reg_File[11] <= 0;
	    Reg_File[12] <= 0; Reg_File[13] <= 0; Reg_File[14] <= 0; Reg_File[15] <= 0;
        Reg_File[16] <= 0; Reg_File[17] <= 0; Reg_File[18] <= 0; Reg_File[19] <= 0;      
        Reg_File[20] <= 0; Reg_File[21] <= 0; Reg_File[22] <= 0; Reg_File[23] <= 0;
        Reg_File[24] <= 0; Reg_File[25] <= 0; Reg_File[26] <= 0; Reg_File[27] <= 0;
        Reg_File[28] <= 0; Reg_File[29] <= 0; Reg_File[30] <= 0; Reg_File[31] <= 0;
	end
    else begin
        if(RegWrite_i) 
            Reg_File[RDaddr_i] <= RDdata_i;	
		else 
		    Reg_File[RDaddr_i] <= Reg_File[RDaddr_i];
	end
end

endmodule

Lab2/Lab2/code/Instr_Memory.v
//Subject:     CO project 2 - Instruction Memory
//--------------------------------------------------------------------------------
//Version:     1
//--------------------------------------------------------------------------------
//Writer:      0616223 0616059
//----------------------------------------------
//Date:        4/27
//----------------------------------------------
//Description: read data
//--------------------------------------------------------------------------------

module Instr_Memory(
    pc_addr_i,
	instr_o
	);
 
//I/O ports
input  [32-1:0]  pc_addr_i;
output [32-1:0]	 instr_o;

//Internal Signals
reg    [32-1:0]	 instr_o;
integer          i;

//32 words Memory
reg    [32-1:0]  Instr_Mem [0:32-1];

//Parameter
    
//Main function
always @(pc_addr_i) begin
	instr_o = Instr_Mem[pc_addr_i/4];
end
    
//Initial Memory Contents
initial begin
    for ( i=0; i<32; i=i+1 )
	    Instr_Mem[i] = 32'b0;
    $readmemb("CO_P2_test_data1.txt", Instr_Mem);  //Read instruction from "CO_P2_test_data1.txt"   
		
end
endmodule

Lab2/Lab2/code/ProgramCounter.v
//Subject:     CO project 2 - PC
//--------------------------------------------------------------------------------
//Version:     1
//--------------------------------------------------------------------------------
//Writer:      0616223 0616059
//----------------------------------------------
//Date:        4/27
//----------------------------------------------
//Description: PC
//--------------------------------------------------------------------------------

module ProgramCounter(
    clk_i,
	rst_i,
	pc_in_i,
	pc_out_o
	);
     
//I/O ports
input           clk_i;
input	        rst_i;
input  [32-1:0] pc_in_i;
output [32-1:0] pc_out_o;
 
//Internal Signals
reg    [32-1:0] pc_out_o;
 
//Parameter

    
//Main function
always @(posedge clk_i) begin
    if(~rst_i)
	    pc_out_o <= 0;
	else
	    pc_out_o <= pc_in_i;
end

endmodule

Lab2/Lab2/code/Simple_Single_CPU.v
//Subject:     CO project 2 - Simple Single CPU
//--------------------------------------------------------------------------------
//Version:     1
//--------------------------------------------------------------------------------
//Writer:      0616223 0616059
//----------------------------------------------
//Date:        4/27	
//----------------------------------------------
//Description: main CPU
//--------------------------------------------------------------------------------
module Simple_Single_CPU(
        clk_i,
		rst_i
		);
		
//I/O port
input         clk_i;
input         rst_i;

//Internal Signles
wire [31:0] pc_out;
wire [31:0] sum_1;
wire [31:0] instr;
wire [5:0] instr_op;
assign instr_op = instr[31:26];
wire [4:0] RSadd;
assign RSadd = instr[25:21];
wire [4:0] RTadd;
assign RTadd = instr[20:16];
wire RegDst;
wire [4:0] muxRD;
assign muxRD = instr[15:11];
wire [4:0] RDadd;
wire RegWrite;
wire [31:0] RSdata;
wire [31:0] RTdata;
wire ALUsrc;
wire Branch;
wire [2:0] ALUOp;
wire [5:0] funct;
assign funct = instr[5:0];
wire [15:0] signi;
assign signi =instr[15:0];
wire [31:0] signo;
wire [31:0] ALUsrc2;
wire [3:0] ALUCtrl;
wire [31:0] Shifto;
wire [31:0] ALUResult;
wire zero;
wire [31:0] ADD2o;
wire bselect;
assign bselect = Branch & zero;
wire [31:0] pc_in;

//wire [31:0] shamt;
//assign shamt = 32'd0;
//assign shamt[4:0] = instr[10:6];
wire select_shamt;
assign select_shamt = (instr[10] | instr[9] | instr[8] | instr[7] | instr[6]) & RegDst & ~Branch;
wire [31:0]shamt_output;
//Greate componentes
ProgramCounter PC(
        .clk_i(clk_i),      
	    .rst_i (rst_i),     
	    .pc_in_i(pc_in) ,   
	    .pc_out_o(pc_out) 
	    );
	
Adder Adder1(
        .src1_i(32'd4),     
	    .src2_i(pc_out),     
	    .sum_o(sum_1)    
	    );
	
Instr_Memory IM(
        .pc_addr_i(pc_out),  
	    .instr_o(instr)    
	    );

MUX_2to1 #(.size(5)) Mux_Write_Reg(
        .data0_i(RTadd),
        .data1_i(muxRD),
        .select_i(RegDst),
        .data_o(RDadd)
        );	
		
Reg_File RF(
        .clk_i(clk_i),      
	    .rst_i(rst_i) ,     
        .RSaddr_i(RSadd) ,  
        .RTaddr_i(RTadd) ,  
        .RDaddr_i(RDadd) ,  
        .RDdata_i(ALUResult)  , 
        .RegWrite_i (RegWrite),
        .RSdata_o(RSdata) ,  
        .RTdata_o(RTdata)   
        );
	
Decoder Decoder(
        .instr_op_i(instr_op), 
	    .RegWrite_o(RegWrite), 
	    .ALU_op_o(ALUOp),   
	    .ALUSrc_o(ALUsrc),   
	    .RegDst_o(RegDst),   
		.Branch_o(Branch)   
	    );

ALU_Ctrl AC(
        .funct_i(funct),   
        .ALUOp_i(ALUOp),   
        .ALUCtrl_o(ALUCtrl) 
        );
	
Sign_Extend SE(
        .data_i(signi),
        .data_o(signo)
        );

MUX_2to1 #(.size(32)) Mux_ALUSrc(
        .data0_i(RTdata),
        .data1_i(signo),
        .select_i(ALUsrc),
        .data_o(ALUsrc2)
        );

MUX_2to1 #(.size(32)) shamt_control(
        .data0_i(RSdata),
        .data1_i(instr),
        .select_i(select_shamt),
        .data_o(shamt_output)
        );      	
		
ALU ALU(
        .src1_i(shamt_output),
	    .src2_i(ALUsrc2),
	    .ctrl_i(ALUCtrl),
	    .result_o(ALUResult),
		.zero_o(zero)
	    );
		
Adder Adder2(
        .src1_i(sum_1),     
	    .src2_i(Shifto),     
	    .sum_o(ADD2o)      
	    );
		
Shift_Left_Two_32 Shifter(
        .data_i(signo),
        .data_o(Shifto)
        ); 		
		
MUX_2to1 #(.size(32)) Mux_PC_Source(
        .data0_i(sum_1),
        .data1_i(ADD2o),
        .select_i(bselect),
        .data_o(pc_in)
        );	

endmodule

Lab2/Lab2/code/Test_Bench.v
//Subject:     CO project 2 - Test Bench
//--------------------------------------------------------------------------------
//Version:     1
//--------------------------------------------------------------------------------
//Writer:      0616223 0616059
//----------------------------------------------
//Date:        4/27
//----------------------------------------------
//Description: testbench
//--------------------------------------------------------------------------------

`define CYCLE_TIME 10			
`define END_COUNT 25
module TestBench;

//Internal Signals
reg         CLK;
reg         RST;
integer     count;
integer     handle;
integer     end_count;
//Greate tested modle  
Simple_Single_CPU cpu(
        .clk_i(CLK),
		.rst_i(RST)
		);
 
//Main function

always #(`CYCLE_TIME/2) CLK = ~CLK;	

initial  begin
	$dumpfile("tb_wave.vcd");
	$dumpvars(0, cpu);

    handle = $fopen("CO_P2_Result.txt");
	CLK = 0;
    RST = 0;
	count = 0;
    end_count=25;
    #(`CYCLE_TIME)      RST = 1;
    #(`CYCLE_TIME*`END_COUNT)	$fclose(handle); $finish;
end

//Print result to "CO_P2_Result.txt"
always@(posedge CLK) begin
    count = count + 1;
	if( count == `END_COUNT ) begin 
    $fdisplay(handle, "r0=%d, r1=%d, r2=%d, r3=%d, r4=%d, r5=%d, r6=%d, r7=%d, r8=%d, r9=%d, r10=%d, r11=%d, r12=%d",
	          cpu.RF.Reg_File[0], cpu.RF.Reg_File[1], cpu.RF.Reg_File[2], cpu.RF.Reg_File[3], cpu.RF.Reg_File[4], 
			  cpu.RF.Reg_File[5], cpu.RF.Reg_File[6], cpu.RF.Reg_File[7], cpu.RF.Reg_File[8], cpu.RF.Reg_File[9], 
			  cpu.RF.Reg_File[10],cpu.RF.Reg_File[11], cpu.RF.Reg_File[12]
			  );
	end
	else ;
end
  
endmodule

Lab2/Lab2/code/tb_wave.vcd
$date
	Sun Apr 28 18:18:21 2019
$end
$version
	Icarus Verilog
$end
$timescale
	1s
$end
$scope module TestBench $end
$scope module cpu $end
$var wire 32 ! ADD2o [31:0] $end
$var wire 4 " ALUCtrl [3:0] $end
$var wire 3 # ALUOp [2:0] $end
$var wire 32 $ ALUResult [31:0] $end
$var wire 1 % ALUsrc $end
$var wire 32 & ALUsrc2 [31:0] $end
$var wire 1 ' Branch $end
$var wire 5 ( RDadd [4:0] $end
$var wire 5 ) RSadd [4:0] $end
$var wire 32 * RSdata [31:0] $end
$var wire 5 + RTadd [4:0] $end
$var wire 32 , RTdata [31:0] $end
$var wire 1 - RegDst $end
$var wire 1 . RegWrite $end
$var wire 32 / Shifto [31:0] $end
$var wire 1 0 bselect $end
$var wire 1 1 clk_i $end
$var wire 6 2 funct [5:0] $end
$var wire 32 3 instr [31:0] $end
$var wire 6 4 instr_op [5:0] $end
$var wire 5 5 muxRD [4:0] $end
$var wire 32 6 pc_in [31:0] $end
$var wire 32 7 pc_out [31:0] $end
$var wire 1 8 rst_i $end
$var wire 1 9 select_shamt $end
$var wire 32 : shamt_output [31:0] $end
$var wire 16 ; signi [15:0] $end
$var wire 32 < signo [31:0] $end
$var wire 32 = sum_1 [31:0] $end
$var wire 1 > zero $end
$scope module PC $end
$var wire 1 1 clk_i $end
$var wire 32 ? pc_in_i [31:0] $end
$var wire 1 8 rst_i $end
$var reg 32 @ pc_out_o [31:0] $end
$upscope $end
$scope module Adder1 $end
$var wire 32 A src1_i [31:0] $end
$var wire 32 B src2_i [31:0] $end
$var wire 32 C sum_o [31:0] $end
$upscope $end
$scope module IM $end
$var wire 32 D pc_addr_i [31:0] $end
$var integer 32 E i [31:0] $end
$var reg 32 F instr_o [31:0] $end
$upscope $end
$scope module Mux_Write_Reg $end
$var wire 5 G data0_i [4:0] $end
$var wire 5 H data1_i [4:0] $end
$var wire 1 - select_i $end
$var reg 5 I data_o [4:0] $end
$upscope $end
$scope module RF $end
$var wire 5 J RDaddr_i [4:0] $end
$var wire 32 K RDdata_i [31:0] $end
$var wire 5 L RSaddr_i [4:0] $end
$var wire 32 M RSdata_o [31:0] $end
$var wire 5 N RTaddr_i [4:0] $end
$var wire 32 O RTdata_o [31:0] $end
$var wire 1 . RegWrite_i $end
$var wire 1 1 clk_i $end
$var wire 1 8 rst_i $end
$upscope $end
$scope module Decoder $end
$var wire 6 P instr_op_i [5:0] $end
$var reg 1 Q ALUSrc_o $end
$var reg 3 R ALU_op_o [2:0] $end
$var reg 1 S Branch_o $end
$var reg 1 T RegDst_o $end
$var reg 1 U RegWrite_o $end
$upscope $end
$scope module AC $end
$var wire 3 V ALUOp_i [2:0] $end
$var wire 6 W funct_i [5:0] $end
$var reg 4 X ALUCtrl_o [3:0] $end
$upscope $end
$scope module SE $end
$var wire 16 Y data_i [15:0] $end
$var reg 32 Z data_o [31:0] $end
$var reg 32 [ i [31:0] $end
$upscope $end
$scope module Mux_ALUSrc $end
$var wire 32 \ data0_i [31:0] $end
$var wire 32 ] data1_i [31:0] $end
$var wire 1 % select_i $end
$var reg 32 ^ data_o [31:0] $end
$upscope $end
$scope module shamt_control $end
$var wire 32 _ data0_i [31:0] $end
$var wire 32 ` data1_i [31:0] $end
$var wire 1 9 select_i $end
$var reg 32 a data_o [31:0] $end
$upscope $end
$scope module ALU $end
$var wire 4 b ctrl_i [3:0] $end
$var wire 32 c src1_i [31:0] $end
$var wire 32 d src2_i [31:0] $end
$var wire 1 > zero_o $end
$var reg 32 e result_o [31:0] $end
$var reg 16 f temp [15:0] $end
$var reg 5 g temp_2 [4:0] $end
$var reg 32 h temp_3 [31:0] $end
$upscope $end
$scope module Adder2 $end
$var wire 32 i src1_i [31:0] $end
$var wire 32 j src2_i [31:0] $end
$var wire 32 k sum_o [31:0] $end
$upscope $end
$scope module Shifter $end
$var wire 32 l data_i [31:0] $end
$var reg 32 m data_o [31:0] $end
$var reg 32 n i [31:0] $end
$upscope $end
$scope module Mux_PC_Source $end
$var wire 32 o data0_i [31:0] $end
$var wire 32 p data1_i [31:0] $end
$var wire 1 0 select_i $end
$var reg 32 q data_o [31:0] $end
$upscope $end
$upscope $end
$upscope $end
$enddefinitions $end
#0
$dumpvars
bx q
bx p
bx o
bx n
bx m
bx l
bx k
bx j
bx i
bx h
bx g
bx f
bx e
bx d
bx c
bx b
bx a
bx `
bx _
bx ^
bx ]
bx \
b100000 [
bx Z
bx Y
bx X
bx W
bx V
xU
xT
xS
bx R
xQ
bx P
bx O
bx N
bx M
bx L
bx K
bx J
bx I
bx H
bx G
bx F
b100000 E
bx D
bx C
bx B
b100 A
bx @
bx ?
x>
bx =
bx <
bx ;
bx :
x9
08
bx 7
bx 6
bx 5
bx 4
bx 3
bx 2
01
x0
bx /
x.
x-
bx ,
bx +
bx *
bx )
bx (
x'
bx &
x%
bx $
bx #
bx "
bx !
$end
#5
0>
b1101 e
b1101 $
b1101 K
b0 a
b0 :
b0 c
b100 q
b100 6
b100 ?
09
b111000 !
b111000 k
b111000 p
b100000 n
b110100 m
b110100 /
b110100 j
b1101 ^
b1101 &
b1101 d
00
b1101 Z
b1101 <
b1101 ]
b1101 l
b100000 [
b10 X
b10 "
b10 b
b1 I
b1 (
b1 J
0S
0'
0T
0-
1U
1.
1Q
1%
b100 R
b100 #
b100 V
b1101 ;
b1101 Y
b1101 2
b1101 W
b0 5
b0 H
b0 ,
b0 O
b0 \
b1 +
b1 G
b1 N
b0 *
b0 M
b0 _
b0 )
b0 L
b1000 4
b1000 P
b100000000000010000000000001101 F
b100000000000010000000000001101 3
b100000000000010000000000001101 `
b0 @
b100 =
b100 C
b100 i
b100 o
b0 7
b0 B
b0 D
11
#10
b1101 ,
b1101 O
b1101 \
01
18
#15
b111 e
b111 $
b111 K
b11100 /
b11100 j
b100000 n
b11100 m
b111 ^
b111 &
b111 d
b111 <
b111 ]
b111 l
b111 Z
b100000 [
b10 I
b10 (
b10 J
b111 ;
b111 Y
b111 2
b111 W
b0 ,
b0 O
b0 \
b10 +
b10 G
b10 N
b1000 q
b1000 6
b1000 ?
b100000000000100000000000000111 F
b100000000000100000000000000111 3
b100000000000100000000000000111 `
b100 @
b100100 !
b100100 k
b100100 p
b1000 =
b1000 C
b1000 i
b1000 o
b100 7
b100 B
b100 D
11
#20
01
#25
0>
b11111111111111111111111111111100 /
b11111111111111111111111111111100 j
b100000 n
b11111111111111111111111111111100 m
b11111111111111111111111111111111 ^
b11111111111111111111111111111111 &
b11111111111111111111111111111111 d
b1 e
b1 $
b1 K
b11111111111111111111111111111111 <
b11111111111111111111111111111111 ]
b11111111111111111111111111111111 l
b11111111111111111111111111111111 Z
b100000 [
b1110 X
b1110 "
b1110 b
b11 I
b11 (
b11 J
b1101 a
b1101 :
b1101 c
b101 R
b101 #
b101 V
b1111111111111111 ;
b1111111111111111 Y
b111111 2
b111111 W
b11111 5
b11111 H
b11 +
b11 G
b11 N
b1101 *
b1101 M
b1101 _
b1 )
b1 L
b1011 4
b1011 P
b1100 q
b1100 6
b1100 ?
b101100001000111111111111111111 F
b101100001000111111111111111111 3
b101100001000111111111111111111 `
b0 ,
b0 O
b0 \
b1000 @
b1000 !
b1000 k
b1000 p
b1100 =
b1100 C
b1100 i
b1100 o
b1000 7
b1000 B
b1000 D
11
#30
01
#35
b100 /
b100 j
b100000 n
b100 m
b1 <
b1 ]
b1 l
b1 Z
b100000 [
b110 X
b110 "
b110 b
b0 ^
b0 &
b0 d
b0 I
b0 (
b0 J
b1 a
b1 :
b1 c
1S
1'
0U
0.
0Q
0%
b1 R
b1 #
b1 V
b1 ;
b1 Y
b1 2
b1 W
b0 5
b0 H
b0 +
b0 G
b0 N
b1 *
b1 M
b1 _
b11 )
b11 L
b100 4
b100 P
b10000 q
b10000 6
b10000 ?
b10000011000000000000000000001 F
b10000011000000000000000000001 3
b10000011000000000000000000001 `
b0 ,
b0 O
b0 \
b1100 @
b10100 !
b10100 k
b10100 p
b10000 =
b10000 C
b10000 i
b10000 o
b1100 7
b1100 B
b1100 D
11
#40
01
#45
b1000000010101000 /
b1000000010101000 j
b100000 n
b1000000010101000 m
b1 e
b1 $
b1 K
b10000000101010 Z
b10000000101010 <
b10000000101010 ]
b10000000101010 l
b100000 [
b111 X
b111 "
b111 b
b1101 ^
b1101 &
b1101 d
b100 I
b100 (
b100 J
b111 a
b111 :
b111 c
0S
0'
1T
1-
1U
1.
b10 R
b10 #
b10 V
b10000000101010 ;
b10000000101010 Y
b101010 2
b101010 W
b100 5
b100 H
b1101 ,
b1101 O
b1101 \
b1 +
b1 G
b1 N
b111 *
b111 M
b111 _
b10 )
b10 L
b0 4
b0 P
b10100 q
b10100 6
b10100 ?
b10000010010000000101010 F
b10000010010000000101010 3
b10000010010000000101010 `
b10000 @
b1000000010111100 !
b1000000010111100 k
b1000000010111100 p
b10100 =
b10100 C
b10100 i
b10100 o
b10000 7
b10000 B
b10000 D
11
#50
01
#55
b1010000010010000 /
b1010000010010000 j
b100000 n
b1010000010010000 m
b10100000100100 <
b10100000100100 ]
b10100000100100 l
b10100000100100 Z
b100000 [
b0 X
b0 "
b0 b
b1 ^
b1 &
b1 d
b101 I
b101 (
b101 J
b1101 a
b1101 :
b1101 c
b10100000100100 ;
b10100000100100 Y
b100100 2
b100100 W
b101 5
b101 H
b1 ,
b1 O
b1 \
b100 +
b100 G
b100 N
b1101 *
b1101 M
b1101 _
b1 )
b1 L
b11000 q
b11000 6
b11000 ?
b1001000010100000100100 F
b1001000010100000100100 3
b1001000010100000100100 `
b10100 @
b1010000010101000 !
b1010000010101000 k
b1010000010101000 p
b11000 =
b11000 C
b11000 i
b11000 o
b10100 7
b10100 B
b10100 D
11
#60
01
#65
b1000000010001100 /
b1000000010001100 j
b100000 n
b1000000010001100 m
b1100 e
b1100 $
b1100 K
b10000000100011 Z
b10000000100011 <
b10000000100011 ]
b10000000100011 l
b100000 [
b110 X
b110 "
b110 b
b100 I
b100 (
b100 J
b10000000100011 ;
b10000000100011 Y
b100011 2
b100011 W
b100 5
b100 H
b101 +
b101 G
b101 N
b11100 q
b11100 6
b11100 ?
b1001010010000000100011 F
b1001010010000000100011 3
b1001010010000000100011 `
b11000 @
b1000000010101000 !
b1000000010101000 k
b1000000010101000 p
b11100 =
b11100 C
b11100 i
b11100 o
b11000 7
b11000 B
b11000 D
11
#70
01
#75
1>
b0 /
b0 j
b100000 n
b0 m
b0 e
b0 $
b0 K
b0 Z
b0 <
b0 ]
b0 l
b100000 [
b0 ^
b0 &
b0 d
b0 I
b0 (
b0 J
b0 a
b0 :
b0 c
b0 ;
b0 Y
b0 2
b0 W
b0 5
b0 H
b0 ,
b0 O
b0 \
b0 +
b0 G
b0 N
b0 *
b0 M
b0 _
b0 )
b0 L
b100000 q
b100000 6
b100000 ?
b0 F
b0 3
b0 `
b11100 @
b100000 !
b100000 k
b100000 p
b100000 =
b100000 C
b100000 i
b100000 o
b11100 7
b11100 B
b11100 D
11
#80
01
#85
b100100 q
b100100 6
b100100 ?
b100000 @
b100100 !
b100100 k
b100100 p
b100100 =
b100100 C
b100100 i
b100100 o
b100000 7
b100000 B
b100000 D
11
#90
01
#95
b101000 q
b101000 6
b101000 ?
b100100 @
b101000 !
b101000 k
b101000 p
b101000 =
b101000 C
b101000 i
b101000 o
b100100 7
b100100 B
b100100 D
11
#100
01
#105
b101100 q
b101100 6
b101100 ?
b101000 @
b101100 !
b101100 k
b101100 p
b101100 =
b101100 C
b101100 i
b101100 o
b101000 7
b101000 B
b101000 D
11
#110
01
#115
b110000 q
b110000 6
b110000 ?
b101100 @
b110000 !
b110000 k
b110000 p
b110000 =
b110000 C
b110000 i
b110000 o
b101100 7
b101100 B
b101100 D
11
#120
01
#125
b110100 q
b110100 6
b110100 ?
b110000 @
b110100 !
b110100 k
b110100 p
b110100 =
b110100 C
b110100 i
b110100 o
b110000 7
b110000 B
b110000 D
11
#130
01
